openspec_mcp/__init__.py
openspec_mcp/__main__.py
openspec_mcp/server.py
openspec_mcp/core/__init__.py
openspec_mcp/core/change_manager.py
openspec_mcp/core/filesystem.py
openspec_mcp/core/init.py
openspec_mcp/core/markdown.py
openspec_mcp/core/spec_manager.py
openspec_mcp/core/validator.py
openspec_mcp/models/__init__.py
openspec_mcp/models/change.py
openspec_mcp/models/spec.py
openspec_mcp/models/validation.py
openspec_mcp/utils/__init__.py
openspec_mcp/utils/errors.py
openspec_mcp/utils/logger.py
openspec_mcp-0.1.0.dist-info/METADATA
openspec_mcp-0.1.0.dist-info/WHEEL
openspec_mcp-0.1.0.dist-info/entry_points.txt
openspec_mcp-0.1.0.dist-info/licenses/LICENSE
openspec_mcp-0.1.0.dist-info/RECORD
