Metadata-Version: 2.4
Name: openspec-mcp
Version: 0.1.0
Summary: MCP server for OpenSpec - AI-native spec-driven development
Project-URL: Homepage, https://github.com/Fission-AI/OpenSpec
Project-URL: Repository, https://github.com/Fission-AI/OpenSpec
Author: OpenSpec Contributors
License: MIT
License-File: LICENSE
Keywords: ai,development,mcp,openspec,specs
Classifier: Development Status :: 3 - Alpha
Classifier: Intended Audience :: Developers
Classifier: License :: OSI Approved :: MIT License
Classifier: Programming Language :: Python :: 3
Classifier: Programming Language :: Python :: 3.10
Classifier: Programming Language :: Python :: 3.11
Classifier: Programming Language :: Python :: 3.12
Requires-Python: >=3.10
Requires-Dist: mcp>=0.9.0
Requires-Dist: pydantic>=2.0.0
Provides-Extra: dev
Requires-Dist: black>=23.0.0; extra == 'dev'
Requires-Dist: mypy>=1.0.0; extra == 'dev'
Requires-Dist: pytest-asyncio>=0.21.0; extra == 'dev'
Requires-Dist: pytest-cov>=4.0.0; extra == 'dev'
Requires-Dist: pytest>=7.0.0; extra == 'dev'
Requires-Dist: ruff>=0.1.0; extra == 'dev'
